Workbook

Sheet PAUTA 1
A1: Pauta de Evaluación de Proyectos | H1: RESUMEN DE LOGRO EVALUACION POR DIMENSIÓN
A3: La escala para la asignación de puntajes en cada descriptor de los criterios a evaluar irá de 1 a 5 con las siguientes consideraciones: | H3: Número | I3: DIMENSION A EVALUAR | J3: Ponderación | K3: Puntaje | L3: (%puntaje)*20
H4: 1 | I4: Ejes estratégicos | J4: 0.2 | K4: =E29 -> 5 | L4: =(K4*J4) -> 1
B5: ESCALA DE PUNTAJES DE EVALUACION | H5: 2 | I5: Análisis de Mercado | J5: 0.1 | K5: =E44 -> 5 | L5: =(K5*J5) -> 0.5
B6: DEFINICIÓN | C6: CATEGORÍA | D6: PUNTAJE | H6: 3 | I6: Análisis de Recursos | J6: 0.1 | K6: =E59 -> 5 | L6: =(K6*J6) -> 0.5
B7: El proyecto no cumple las exigencias del programa. | C7: Deficiente | D7: 1 | H7: 4 | I7: Actividades del proyecto | J7: 0.1 | K7: =E76 -> 5 | L7: =(K7*J7) -> 0.5
B8: El proyecto presenta debilidades significativas respecto de las exigencias del programa. | C8: Insuficiente | D8: 2 | H8: 5 | I8: Conceptos Económicos | J8: 0.2 | K8: =E94 -> 5 | L8: =(K8*J8) -> 1
B9: El proyecto se ajusta mínimamente a las exigencias del programa y no satisface lo requerido. | C9: Regular | D9: 3 | H9: 6 | I9: Rentabilidad Económica | J9: 0.3 | K9: =E107 -> 5 | L9: =(K9*J9) -> 1.5
B10: El proyecto satisface y a veces supera las exigencias del programa. | C10: Bueno | D10: 4 | I10: TOTAL DIMENSION III | J10: =SUM(J4:J9) -> 1 | L10: =SUM(L4:L9) -> 5
B11: El proyecto siempre satisface y en la mayoría de sus propuestas supera las exigencias del programa. | C11: Excelente | D11: 5
H12: OBSERVACIONES GENERALES:
A13: Las observaciones derivadas de esta Pauta en sus cuadros de fortalezas y debilidades, así como en Observaciones Generales serán consideradas como parte del seguimiento de la supervisión técnica que se realizará una vez adjudicado el proyecto y puesto en marcha.
A15: I. DATOS GENERALES
A16: PERIODO DE EVALUACIÓN | B16: Marzo 2025 - Junio 2025
A17: NOMBRE DEL PROYECTO | B17: Pagina Web Hostal-Soft
A18: EJE ESTRATÉGICO AL CUAL SE DIRIGE | B18: Gestión web de hostales de clientes
A19: PUNTAJE FINAL | B19: =L10 -> 5
A23: 1.- | B23: Criterio : Relación del proyecto con los ejes estratégicos de la organización | C23: Ponderador % (A) | D23: Puntaje (B) | E23: (% puntaje) (C)
B24: DESCRIPTORES
A25: 1 | B25: Analiza de manera objetiva los ejes estratégicos correspondientes a la Municipalidad. | C25: 0.2 | D25: 5 | E25: =(D25*C25) -> 1
A26: 2 | B26: Relaciona el proyecto con un eje estratégico de la organización. | C26: 0.3 | D26: 5 | E26: =(D26*C26) -> 1.5
A27: 3 | B27: Define el propósito del proyecto con la finalidad de establecer que problema específico resolverá. | C27: 0.2 | D27: 5 | E27: =(D27*C27) -> 1
A28: 4 | B28: Declara con claridad el proyecto con el fin de entender el propósito del mismo. | C28: 0.3 | D28: 5 | E28: =(D28*C28) -> 1.5
B29: PUNTAJE TOTAL | C29: =SUM(C25:C28) -> 1 | E29: =SUM(E25:E28) -> 5
B31: Observaciones: fundamente brevemente la calificación asignada
B32: Fortalezas | C32: Debilidades
B33: Recursividad de codigo realizado por desarrollo de pagina | C33: 3 mesesde desarrollo
A37: 2.- | B37: Criterio : Analiza el mercado objetivo del proyecto | C37: Ponderador % (A) | D37: Puntaje (B) | E37: (% puntaje) (C)
B38: DESCRIPTORES
A39: 1 | B39: Realiza un instrumento para la realización del Estudio de Mercado para conocer la aceptación del proyecto en la comunidad | C39: 0.25 | D39: 5 | E39: =(D39*C39) -> 1.25
A40: 2 | B40: Identifica aspectos relevantes para la realización del proyecto en base al Estudio de Mercado. | C40: 0.25 | D40: 5 | E40: =(D40*C40) -> 1.25
A41: 3 | B41: Identifica el tamaño de la muestra según los parámetros expuestos por el docente. | C41: 0.2 | D41: 5 | E41: =(D41*C41) -> 1
A42: 4 | B42: Analiza de manera genérica la competencia, con el fin de obtener referencias en el precio del producto. | C42: 0.1 | D42: 5 | E42: =(D42*C42) -> 0.5
A43: 5 | B43: Determina la comercialización del producto en base a criterios acordes al tipo de producto a ofrecer | C43: 0.2 | D43: 5 | E43: =(D43*C43) -> 1
B44: PUNTAJE TOTAL | C44: =SUM(C39:C43) -> 1 | E44: =SUM(E39:E43) -> 5
B46: Observaciones: fundamente brevemente la calificación asignada
B47: Fortalezas | C47: Debilidades
A52: 3.- | B52: Criterio : Establece los recursos óptimos para el desarrollo del proyecto | C52: Ponderador % (A) | D52: Puntaje (B) | E52: (% puntaje) (C)
B53: DESCRIPTORES
A54: 1 | B54: Identifica los recursos humanos necesarios para el desarrollo del proyecto | C54: 0.2 | D54: 5 | E54: =(D54*C54) -> 1
A55: 2 | B55: Identifica los recursos materiales necesarios para el desarrollo del proyecto | C55: 0.2 | D55: 5 | E55: =(D55*C55) -> 1
A56: 3 | B56: Identifica la infraestructura necesaria para el desarrollo del proyecto | C56: 0.2 | D56: 5 | E56: =(D56*C56) -> 1
A57: 4 | B57: Identifica los aspectos legales necesarios para el desarrollo del proyecto. | C57: 0.2 | D57: 5 | E57: =(D57*C57) -> 1
A58: 5 | B58: Justifica la determinación geográfica del proyecto basados en una tabla comparativa con ponderación de los aspectos a evaluar. | C58: 0.2 | D58: 5 | E58: =(D58*C58) -> 1
B59: PUNTAJE TOTAL | C59: =SUM(C54:C58) -> 1 | E59: =SUM(E54:E58) -> 5
B61: Observaciones: fundamente brevemente la calificación asignada
B62: Fortalezas | C62: Debilidades
A68: 4.- | B68: Criterio: Relaciona los recursos con las actividades a desarrollar en el proyecto | C68: Ponderador % (A) | D68: Puntaje (B) | E68: (% puntaje) (C)
B69: DESCRIPTORES
A70: 1 | B70: Desarrolla la EDT del proyecto analizando las actividades involucradas en el mismo | C70: 0.15 | D70: 5 | E70: =(D70*C70) -> 0.75
A71: 2 | B71: Genera un cronograma de actividades estableciendo etapas de acuerdo a las necesidades del proyecto | C71: 0.2 | D71: 5 | E71: =(D71*C71) -> 1
A72: 3 | B72: Establece actividades relacionadas a la magnitud del proyecto | C72: 0.3 | D72: 5 | E72: =(D72*C72) -> 1.5
A73: 4 | B73: Realiza un resumen de costos en recursos humanos, en relación a las actividades expresadas en el cronograma | C73: 0.1 | D73: 5 | E73: =(D73*C73) -> 0.5
A74: 5 | B74: Realiza el cálculo de Reserva de contingencia acorde a los riesgos identificados por el equipo | C74: 0.15 | D74: 5 | E74: =(D74*C74) -> 0.75
A75: 6 | B75: Determina factores ambientales para el cálculo de los costos asociados al proyecto. | C75: 0.1 | D75: 5 | E75: =(D75*C75) -> 0.5
B76: PUNTAJE TOTAL | C76: =SUM(C70:C75) -> 1 | E76: =SUM(E70:E75) -> 5
B78: Observaciones: fundamente brevemente la calificación asignada
B79: Fortalezas | C79: Debilidades
A84: 5.- | B84: Criterio : Establece conceptos económicos relacionados con el proyecto | C84: Ponderador % (A) | D84: Puntaje (B) | E84: (% puntaje) (C)
A85: 1 | B85: La estructura del flujo de caja es acorde al proyecto a realizar | C85: 0.05 | D85: 5 | E85: =(D85*C85) -> 0.25
A86: 2 | B86: Establece valores en el flujo de caja acordes a las necesidades del proyecto | C86: 0.15 | D86: 5 | E86: =(D86*C86) -> 0.75
A87: 3 | B87: Realiza las operaciones matemáticas de manera correcta dentro del flujo de caja | C87: 0.1 | D87: 5 | E87: =(D87*C87) -> 0.5
A88: 4 | B88: Establece una inversión inicial acorde a las necesidades del proyecto | C88: 0.1 | D88: 5 | E88: =(D88*C88) -> 0.5
A89: 5 | B89: Establece el punto de equilibrio de manera correcta de acuerdo a los datos del proyecto | C89: 0.1 | D89: 5 | E89: =(D89*C89) -> 0.5
A90: 6 | B90: Establece el período de recuperación de capital de manera correcta de acuerdo a los datos del proyecto | C90: 0.1 | D90: 5 | E90: =(D90*C90) -> 0.5
A91: 7 | B91: Determina el VAN del proyecto de manera correcta de acuerdo a la información entregada en el flujo de caja | C91: 0.15 | D91: 5 | E91: =(D91*C91) -> 0.75
A92: 8 | B92: Determina la TIR de manera correcta de acuerdo a la información entregada en el flujo de caja | C92: 0.15 | D92: 5 | E92: =(D92*C92) -> 0.75
A93: 9 | B93: Establece de manera correcta las cuotas del préstamo a pagar para cubrir la inversión inicial en relación al porcentaje solicitado | C93: 0.1 | D93: 5 | E93: =(D93*C93) -> 0.5
B94: PUNTAJE TOTAL | C94: =SUM(C85:C93) -> 1 | E94: =SUM(E85:E93) -> 5
B96: Observaciones: fundamente brevemente la calificación asignada
B97: Fortalezas | C97: Debilidades
A102: 6.- | B102: Criterio : Determina factores económicos que demuestran la factibilidad del proyecto | C102: Ponderador % (A) | D102: Puntaje (B) | E102: (% puntaje) (C)
B103: DESCRIPTORES
A104: a | B104: El período de recuperación es acorde a la duración del proyecto | C104: 0.2 | D104: 5 | E104: =(D104*C104) -> 1
A105: b | B105: La TIR es positiva, determinando que el proyecto es conveniente realizarlo | C105: 0.4 | D105: 5 | E105: =(D105*C105) -> 2
A106: c | B106: La VAN es positiva, determinando que el proyecto es conveniente realizarlo | C106: 0.4 | D106: 5 | E106: =(D106*C106) -> 2
B107: PUNTAJE TOTAL | C107: =SUM(C104:C106) -> 1 | E107: =SUM(E104:E106) -> 5
B109: Observaciones: fundamente brevemente la calificación asignada
B110: Fortalezas | C110: Debilidades

Sheet PAUTA 2
A1: Pauta de Evaluación de Proyectos | H1: RESUMEN DE LOGRO EVALUACION POR DIMENSIÓN
A3: La escala para la asignación de puntajes en cada descriptor de los criterios a evaluar irá de 1 a 5 con las siguientes consideraciones: | H3: Número | I3: DIMENSION A EVALUAR | J3: Ponderación | K3: Puntaje | L3: (%puntaje)*20
H4: 1 | I4: Ejes estratégicos | J4: 0.2 | K4: =E29 -> 0 | L4: =(K4*J4) -> 0
B5: ESCALA DE PUNTAJES DE EVALUACION | H5: 2 | I5: Análisis de Mercado | J5: 0.1 | K5: =E44 -> 0 | L5: =(K5*J5) -> 0
B6: DEFINICIÓN | C6: CATEGORÍA | D6: PUNTAJE | H6: 3 | I6: Análisis de Recursos | J6: 0.1 | K6: =E59 -> 0 | L6: =(K6*J6) -> 0
B7: El proyecto no cumple las exigencias del programa. | C7: Deficiente | D7: 1 | H7: 4 | I7: Actividades del proyecto | J7: 0.1 | K7: =E76 -> 0 | L7: =(K7*J7) -> 0
B8: El proyecto presenta debilidades significativas respecto de las exigencias del programa. | C8: Insuficiente | D8: 2 | H8: 5 | I8: Conceptos Económicos | J8: 0.2 | K8: =E94 -> 0 | L8: =(K8*J8) -> 0
B9: El proyecto se ajusta mínimamente a las exigencias del programa y no satisface lo requerido. | C9: Regular | D9: 3 | H9: 6 | I9: Rentabilidad Económica | J9: 0.3 | K9: =E107 -> 0 | L9: =(K9*J9) -> 0
B10: El proyecto satisface y a veces supera las exigencias del programa. | C10: Bueno | D10: 4 | I10: TOTAL DIMENSION III | J10: =SUM(J4:J9) -> 1 | L10: =SUM(L7:L9) -> 0
B11: El proyecto siempre satisface y en la mayoría de sus propuestas supera las exigencias del programa. | C11: Excelente | D11: 5
H12: OBSERVACIONES GENERALES:
A13: Las observaciones derivadas de esta Pauta en sus cuadros de fortalezas y debilidades, así como en Observaciones Generales serán consideradas como parte del seguimiento de la supervisión técnica que se realizará una vez adjudicado el proyecto y puesto en marcha.
A15: I. DATOS GENERALES
A16: PERIODO DE EVALUACIÓN
A17: NOMBRE DEL PROYECTO
A18: EJE ESTRATÉGICO AL CUAL SE DIRIGE
A19: PUNTAJE FINAL | B19: =L10 -> 0
A23: 1.- | B23: Criterio : Relación del proyecto con los ejes estratégicos de la organización | C23: Ponderador % (A) | D23: Puntaje (B) | E23: (% puntaje) (C)
B24: DESCRIPTORES
A25: 1 | B25: Analiza de manera objetiva los ejes estratégicos correspondientes a la Municipalidad. | C25: 0.2 | E25: =(D25*C25) -> 0
A26: 2 | B26: Relaciona el proyecto con un eje estratégico de la organización. | C26: 0.3 | E26: =(D26*C26) -> 0
A27: 3 | B27: Define el propósito del proyecto con la finalidad de establecer que problema específico resolverá. | C27: 0.2 | E27: =(D27*C27) -> 0
A28: 4 | B28: Declara con claridad el proyecto con el fin de entender el propósito del mismo. | C28: 0.3 | E28: =(D28*C28) -> 0
B29: PUNTAJE TOTAL | C29: =SUM(C25:C28) -> 1 | E29: =SUM(E25:E28) -> 0
B31: Observaciones: fundamente brevemente la calificación asignada
B32: Fortalezas | C32: Debilidades
A37: 2.- | B37: Criterio : Analiza el mercado objetivo del proyecto | C37: Ponderador % (A) | D37: Puntaje (B) | E37: (% puntaje) (C)
B38: DESCRIPTORES
A39: 1 | B39: Realiza un instrumento para la realización del Estudio de Mercado para conocer la aceptación del proyecto en la comunidad | C39: 0.25 | E39: =(D39*C39) -> 0
A40: 2 | B40: Identifica aspectos relevantes para la realización del proyecto en base al Estudio de Mercado. | C40: 0.25 | E40: =(D40*C40) -> 0
A41: 3 | B41: Identifica el tamaño de la muestra según los parámetros expuestos por el docente. | C41: 0.2 | E41: =(D41*C41) -> 0
A42: 4 | B42: Analiza de manera genérica la competencia, con el fin de obtener referencias en el precio del producto. | C42: 0.1 | E42: =(D42*C42) -> 0
A43: 5 | B43: Determina la comercialización del producto en base a criterios acordes al tipo de producto a ofrecer | C43: 0.2 | E43: =(D43*C43) -> 0
B44: PUNTAJE TOTAL | C44: =SUM(C39:C43) -> 1 | E44: =SUM(E39:E43) -> 0
B46: Observaciones: fundamente brevemente la calificación asignada
B47: Fortalezas | C47: Debilidades
A52: 3.- | B52: Criterio : Establece los recursos óptimos para el desarrollo del proyecto | C52: Ponderador % (A) | D52: Puntaje (B) | E52: (% puntaje) (C)
B53: DESCRIPTORES
A54: 1 | B54: Identifica los recursos humanos necesarios para el desarrollo del proyecto | C54: 0.2 | E54: =(D54*C54) -> 0
A55: 2 | B55: Identifica los recursos materiales necesarios para el desarrollo del proyecto | C55: 0.2 | E55: =(D55*C55) -> 0
A56: 3 | B56: Identifica la infraestructura necesaria para el desarrollo del proyecto | C56: 0.2 | E56: =(D56*C56) -> 0
A57: 4 | B57: Identifica los aspectos legales necesarios para el desarrollo del proyecto. | C57: 0.2 | E57: =(D57*C57) -> 0
A58: 5 | B58: Justifica la determinación geográfica del proyecto basados en una tabla comparativa con ponderación de los aspectos a evaluar. | C58: 0.2 | E58: =(D58*C58) -> 0
B59: PUNTAJE TOTAL | C59: =SUM(C54:C58) -> 1 | E59: =SUM(E54:E58) -> 0
B61: Observaciones: fundamente brevemente la calificación asignada
B62: Fortalezas | C62: Debilidades
A68: 4.- | B68: Criterio: Relaciona los recursos con las actividades a desarrollar en el proyecto | C68: Ponderador % (A) | D68: Puntaje (B) | E68: (% puntaje) (C)
B69: DESCRIPTORES
A70: 1 | B70: Desarrolla la EDT del proyecto analizando las actividades involucradas en el mismo | C70: 0.15 | E70: =(D70*C70) -> 0
A71: 2 | B71: Genera un cronograma de actividades estableciendo etapas de acuerdo a las necesidades del proyecto | C71: 0.2 | E71: =(D71*C71) -> 0
A72: 3 | B72: Establece actividades relacionadas a la magnitud del proyecto | C72: 0.3 | E72: =(D72*C72) -> 0
A73: 4 | B73: Realiza un resumen de costos en recursos humanos, en relación a las actividades expresadas en el cronograma | C73: 0.1 | E73: =(D73*C73) -> 0
A74: 5 | B74: Realiza el cálculo de Reserva de contingencia acorde a los riesgos identificados por el equipo | C74: 0.15 | E74: =(D74*C74) -> 0
A75: 6 | B75: Determina factores ambientales para el cálculo de los costos asociados al proyecto. | C75: 0.1 | E75: =(D75*C75) -> 0
B76: PUNTAJE TOTAL | C76: =SUM(C70:C75) -> 1 | E76: =SUM(E70:E75) -> 0
B78: Observaciones: fundamente brevemente la calificación asignada
B79: Fortalezas | C79: Debilidades
A84: 5.- | B84: Criterio : Establece conceptos económicos relacionados con el proyecto | C84: Ponderador % (A) | D84: Puntaje (B) | E84: (% puntaje) (C)
A85: 1 | B85: La estructura del flujo de caja es acorde al proyecto a realizar | C85: 0.05 | E85: =(D85*C85) -> 0
A86: 2 | B86: Establece valores en el flujo de caja acordes a las necesidades del proyecto | C86: 0.15 | E86: =(D86*C86) -> 0
A87: 3 | B87: Realiza las operaciones matemáticas de manera correcta dentro del flujo de caja | C87: 0.1 | E87: =(D87*C87) -> 0
A88: 4 | B88: Establece una inversión inicial acorde a las necesidades del proyecto | C88: 0.1 | E88: =(D88*C88) -> 0
A89: 5 | B89: Establece el punto de equilibrio de manera correcta de acuerdo a los datos del proyecto | C89: 0.1 | E89: =(D89*C89) -> 0
A90: 6 | B90: Establece el período de recuperación de capital de manera correcta de acuerdo a los datos del proyecto | C90: 0.1 | E90: =(D90*C90) -> 0
A91: 7 | B91: Determina el VAN del proyecto de manera correcta de acuerdo a la información entregada en el flujo de caja | C91: 0.15 | E91: =(D91*C91) -> 0
A92: 8 | B92: Determina la TIR de manera correcta de acuerdo a la información entregada en el flujo de caja | C92: 0.15 | E92: =(D92*C92) -> 0
A93: 9 | B93: Establece de manera correcta las cuotas del préstamo a pagar para cubrir la inversión inicial en relación al porcentaje solicitado | C93: 0.1 | E93: =(D93*C93) -> 0
B94: PUNTAJE TOTAL | C94: =SUM(C85:C93) -> 1 | E94: =SUM(E85:E93) -> 0
B96: Observaciones: fundamente brevemente la calificación asignada
B97: Fortalezas | C97: Debilidades
A102: 6.- | B102: Criterio : Determina factores económicos que demuestran la factibilidad del proyecto | C102: Ponderador % (A) | D102: Puntaje (B) | E102: (% puntaje) (C)
B103: DESCRIPTORES
A104: a | B104: El período de recuperación es acorde a la duración del proyecto | C104: 0.2 | E104: =(D104*C104) -> 0
A105: b | B105: La TIR es positiva, determinando que el proyecto es conveniente realizarlo | C105: 0.4 | E105: =(D105*C105) -> 0
A106: c | B106: La VAN es positiva, determinando que el proyecto es conveniente realizarlo | C106: 0.4 | E106: =(D106*C106) -> 0
B107: PUNTAJE TOTAL | C107: =SUM(C104:C106) -> 1 | E107: =SUM(E104:E106) -> 0
B109: Observaciones: fundamente brevemente la calificación asignada
B110: Fortalezas | C110: Debilidades

Sheet PAUTA 3
A1: Pauta de Evaluación de Proyectos | H1: RESUMEN DE LOGRO EVALUACION POR DIMENSIÓN
A3: La escala para la asignación de puntajes en cada descriptor de los criterios a evaluar irá de 1 a 5 con las siguientes consideraciones: | H3: Número | I3: DIMENSION A EVALUAR | J3: Ponderación | K3: Puntaje | L3: (%puntaje)*20
H4: 1 | I4: Ejes estratégicos | J4: 0.2 | K4: =E29 -> 5 | L4: =(K4*J4) -> 1
B5: ESCALA DE PUNTAJES DE EVALUACION | H5: 2 | I5: Análisis de Mercado | J5: 0.1 | K5: =E44 -> 3.5 | L5: =(K5*J5) -> 0.35
B6: DEFINICIÓN | C6: CATEGORÍA | D6: PUNTAJE | H6: 3 | I6: Análisis de Recursos | J6: 0.1 | K6: =E60 -> 5 | L6: =(K6*J6) -> 0.5
B7: El proyecto no cumple las exigencias del programa. | C7: Deficiente | D7: 1 | H7: 4 | I7: Actividades del proyecto | J7: 0.1 | K7: =E77 -> 2.3 | L7: =(K7*J7) -> 0.23
B8: El proyecto presenta debilidades significativas respecto de las exigencias del programa. | C8: Insuficiente | D8: 2 | H8: 5 | I8: Conceptos Económicos | J8: 0.2 | K8: =E95 -> 5 | L8: =(K8*J8) -> 1
B9: El proyecto se ajusta mínimamente a las exigencias del programa y no satisface lo requerido. | C9: Regular | D9: 3 | H9: 6 | I9: Rentabilidad Económica | J9: 0.3 | K9: =E108 -> 5 | L9: =(K9*J9) -> 1.5
B10: El proyecto satisface y a veces supera las exigencias del programa. | C10: Bueno | D10: 4 | I10: TOTAL DIMENSION III | J10: =SUM(J4:J9) -> 1 | L10: =SUM(L4:L9) -> 4.58
B11: El proyecto siempre satisface y en la mayoría de sus propuestas supera las exigencias del programa. | C11: Excelente | D11: 5
H12: OBSERVACIONES GENERALES:
A13: Las observaciones derivadas de esta Pauta en sus cuadros de fortalezas y debilidades, así como en Observaciones Generales serán consideradas como parte del seguimiento de la supervisión técnica que se realizará una vez adjudicado el proyecto y puesto en marcha.
A15: I. DATOS GENERALES
A16: PERIODO DE EVALUACIÓN | B16: Junio 2025 - Julio 2025
A17: NOMBRE DEL PROYECTO | B17: Web Movil Hostal-Soft
A18: EJE ESTRATÉGICO AL CUAL SE DIRIGE | B18: Tecnologia portable para clientes
A19: PUNTAJE FINAL | B19: =L10 -> 4.58
A23: 1.- | B23: Criterio : Relación del proyecto con los ejes estratégicos de la organización | C23: Ponderador % (A) | D23: Puntaje (B) | E23: (% puntaje) (C)
B24: DESCRIPTORES
A25: 1 | B25: Analiza de manera objetiva los ejes estratégicos correspondientes a la Municipalidad. | C25: 0.2 | D25: 5 | E25: =(D25*C25) -> 1
A26: 2 | B26: Relaciona el proyecto con un eje estratégico de la organización. | C26: 0.3 | D26: 5 | E26: =(D26*C26) -> 1.5
A27: 3 | B27: Define el propósito del proyecto con la finalidad de establecer que problema específico resolverá. | C27: 0.2 | D27: 5 | E27: =(D27*C27) -> 1
A28: 4 | B28: Declara con claridad el proyecto con el fin de entender el propósito del mismo. | C28: 0.3 | D28: 5 | E28: =(D28*C28) -> 1.5
B29: PUNTAJE TOTAL | C29: =SUM(C25:C28) -> 1 | E29: =SUM(E25:E28) -> 5
B31: Observaciones: fundamente brevemente la calificación asignada
B32: Fortalezas | C32: Debilidades
B33: - Mayor portabilidad al proyecto - Más amigable con el usuario - Solo requiere reutilizar algunos recursos ya existentes para su desarollo
A37: 2.- | B37: Criterio : Analiza el mercado objetivo del proyecto | C37: Ponderador % (A) | D37: Puntaje (B) | E37: (% puntaje) (C)
B38: DESCRIPTORES
A39: 1 | B39: Realiza un instrumento para la realización del Estudio de Mercado para conocer la aceptación del proyecto en la comunidad | C39: 0.25 | D39: 5 | E39: =(D39*C39) -> 1.25
A40: 2 | B40: Identifica aspectos relevantes para la realización del proyecto en base al Estudio de Mercado. | C40: 0.25 | D40: 5 | E40: =(D40*C40) -> 1.25
A41: 3 | B41: Identifica el tamaño de la muestra según los parámetros expuestos por el docente. | C41: 0.2 | D41: 2 | E41: =(D41*C41) -> 0.4
A42: 4 | B42: Analiza de manera genérica la competencia, con el fin de obtener referencias en el precio del producto. | C42: 0.1 | D42: 4 | E42: =(D42*C42) -> 0.4
A43: 5 | B43: Determina la comercialización del producto en base a criterios acordes al tipo de producto a ofrecer | C43: 0.2 | D43: 1 | E43: =(D43*C43) -> 0.2
B44: PUNTAJE TOTAL | C44: =SUM(C39:C43) -> 1 | E44: =SUM(E39:E43) -> 3.5
B46: Observaciones: fundamente brevemente la calificación asignada
B47: Fortalezas | C47: Debilidades
B48: - La mayoria de los usuarios tiene un smartphone y saben usarlos parar realizar procesos y completar formularios - Muchas empresas ya estan implementando este tipo de soluciones | C48: - La tercera edad requiere mayor capacitacion
A53: 3.- | B53: Criterio : Establece los recursos óptimos para el desarrollo del proyecto | C53: Ponderador % (A) | D53: Puntaje (B) | E53: (% puntaje) (C)
B54: DESCRIPTORES
A55: 1 | B55: Identifica los recursos humanos necesarios para el desarrollo del proyecto | C55: 0.2 | D55: 5 | E55: =(D55*C55) -> 1
A56: 2 | B56: Identifica los recursos materiales necesarios para el desarrollo del proyecto | C56: 0.2 | D56: 5 | E56: =(D56*C56) -> 1
A57: 3 | B57: Identifica la infraestructura necesaria para el desarrollo del proyecto | C57: 0.2 | D57: 5 | E57: =(D57*C57) -> 1
A58: 4 | B58: Identifica los aspectos legales necesarios para el desarrollo del proyecto. | C58: 0.2 | D58: 5 | E58: =(D58*C58) -> 1
A59: 5 | B59: Justifica la determinación geográfica del proyecto basados en una tabla comparativa con ponderación de los aspectos a evaluar. | C59: 0.2 | D59: 5 | E59: =(D59*C59) -> 1
B60: PUNTAJE TOTAL | C60: =SUM(C55:C59) -> 1 | E60: =SUM(E55:E59) -> 5
B62: Observaciones: fundamente brevemente la calificación asignada
B63: Fortalezas | C63: Debilidades
B64: - Las personas asignadas ya conocen el proyecto web - Se requere reutilizar recursos del proyecto web para adaptar a este proyecto - tomará poco tiempo su desarrollo
A69: 4.- | B69: Criterio: Relaciona los recursos con las actividades a desarrollar en el proyecto | C69: Ponderador % (A) | D69: Puntaje (B) | E69: (% puntaje) (C)
B70: DESCRIPTORES
A71: 1 | B71: Desarrolla la EDT del proyecto analizando las actividades involucradas en el mismo | C71: 0.15 | D71: 4 | E71: =(D71*C71) -> 0.6
A72: 2 | B72: Genera un cronograma de actividades estableciendo etapas de acuerdo a las necesidades del proyecto | C72: 0.2 | D72: 2 | E72: =(D72*C72) -> 0.4
A73: 3 | B73: Establece actividades relacionadas a la magnitud del proyecto | C73: 0.3 | D73: 1 | E73: =(D73*C73) -> 0.3
A74: 4 | B74: Realiza un resumen de costos en recursos humanos, en relación a las actividades expresadas en el cronograma | C74: 0.1 | D74: 3 | E74: =(D74*C74) -> 0.3
A75: 5 | B75: Realiza el cálculo de Reserva de contingencia acorde a los riesgos identificados por el equipo | C75: 0.15 | D75: 2 | E75: =(D75*C75) -> 0.3
A76: 6 | B76: Determina factores ambientales para el cálculo de los costos asociados al proyecto. | C76: 0.1 | D76: 4 | E76: =(D76*C76) -> 0.4
B77: PUNTAJE TOTAL | C77: =SUM(C71:C76) -> 1 | E77: =SUM(E71:E76) -> 2.3
B79: Observaciones: fundamente brevemente la calificación asignada
B80: Fortalezas | C80: Debilidades
B81: - Los costos son bajos debido a que reutilizan recursos ya usado en otro proyecto - Los riesgos son conocidos por el equipo ya que esta relacionado a otro proyecto anterior
A85: 5.- | B85: Criterio : Establece conceptos económicos relacionados con el proyecto | C85: Ponderador % (A) | D85: Puntaje (B) | E85: (% puntaje) (C)
A86: 1 | B86: La estructura del flujo de caja es acorde al proyecto a realizar | C86: 0.05 | D86: 5 | E86: =(D86*C86) -> 0.25
A87: 2 | B87: Establece valores en el flujo de caja acordes a las necesidades del proyecto | C87: 0.15 | D87: 5 | E87: =(D87*C87) -> 0.75
A88: 3 | B88: Realiza las operaciones matemáticas de manera correcta dentro del flujo de caja | C88: 0.1 | D88: 5 | E88: =(D88*C88) -> 0.5
A89: 4 | B89: Establece una inversión inicial acorde a las necesidades del proyecto | C89: 0.1 | D89: 5 | E89: =(D89*C89) -> 0.5
A90: 5 | B90: Establece el punto de equilibrio de manera correcta de acuerdo a los datos del proyecto | C90: 0.1 | D90: 5 | E90: =(D90*C90) -> 0.5
A91: 6 | B91: Establece el período de recuperación de capital de manera correcta de acuerdo a los datos del proyecto | C91: 0.1 | D91: 5 | E91: =(D91*C91) -> 0.5
A92: 7 | B92: Determina el VAN del proyecto de manera correcta de acuerdo a la información entregada en el flujo de caja | C92: 0.15 | D92: 5 | E92: =(D92*C92) -> 0.75
A93: 8 | B93: Determina la TIR de manera correcta de acuerdo a la información entregada en el flujo de caja | C93: 0.15 | D93: 5 | E93: =(D93*C93) -> 0.75
A94: 9 | B94: Establece de manera correcta las cuotas del préstamo a pagar para cubrir la inversión inicial en relación al porcentaje solicitado | C94: 0.1 | D94: 5 | E94: =(D94*C94) -> 0.5
B95: PUNTAJE TOTAL | C95: =SUM(C86:C94) -> 1 | E95: =SUM(E86:E94) -> 5
B97: Observaciones: fundamente brevemente la calificación asignada
B98: Fortalezas | C98: Debilidades
A103: 6.- | B103: Criterio : Determina factores económicos que demuestran la factibilidad del proyecto | C103: Ponderador % (A) | D103: Puntaje (B) | E103: (% puntaje) (C)
B104: DESCRIPTORES
A105: a | B105: El período de recuperación es acorde a la duración del proyecto | C105: 0.2 | D105: 5 | E105: =(D105*C105) -> 1
A106: b | B106: La TIR es positiva, determinando que el proyecto es conveniente realizarlo | C106: 0.4 | D106: 5 | E106: =(D106*C106) -> 2
A107: c | B107: La VAN es positiva, determinando que el proyecto es conveniente realizarlo | C107: 0.4 | D107: 5 | E107: =(D107*C107) -> 2
B108: PUNTAJE TOTAL | C108: =SUM(C105:C107) -> 1 | E108: =SUM(E105:E107) -> 5
B110: Observaciones: fundamente brevemente la calificación asignada
B111: Fortalezas | C111: Debilidades

Sheet PAUTA 4
A1: Pauta de Evaluación de Proyectos | H1: RESUMEN DE LOGRO EVALUACION POR DIMENSIÓN
A3: La escala para la asignación de puntajes en cada descriptor de los criterios a evaluar irá de 1 a 5 con las siguientes consideraciones: | H3: Número | I3: DIMENSION A EVALUAR | J3: Ponderación | K3: Puntaje | L3: (%puntaje)*20
H4: 1 | I4: Ejes estratégicos | J4: 0.2 | K4: =E29 -> 0 | L4: =(K4*J4) -> 0
B5: ESCALA DE PUNTAJES DE EVALUACION | H5: 2 | I5: Análisis de Mercado | J5: 0.1 | K5: =E44 -> 0 | L5: =(K5*J5) -> 0
B6: DEFINICIÓN | C6: CATEGORÍA | D6: PUNTAJE | H6: 3 | I6: Análisis de Recursos | J6: 0.1 | K6: =E59 -> 0 | L6: =(K6*J6) -> 0
B7: El proyecto no cumple las exigencias del programa. | C7: Deficiente | D7: 1 | H7: 4 | I7: Actividades del proyecto | J7: 0.1 | K7: =E76 -> 0 | L7: =(K7*J7) -> 0
B8: El proyecto presenta debilidades significativas respecto de las exigencias del programa. | C8: Insuficiente | D8: 2 | H8: 5 | I8: Conceptos Económicos | J8: 0.2 | K8: =E94 -> 0 | L8: =(K8*J8) -> 0
B9: El proyecto se ajusta mínimamente a las exigencias del programa y no satisface lo requerido. | C9: Regular | D9: 3 | H9: 6 | I9: Rentabilidad Económica | J9: 0.3 | K9: =E107 -> 0 | L9: =(K9*J9) -> 0
B10: El proyecto satisface y a veces supera las exigencias del programa. | C10: Bueno | D10: 4 | I10: TOTAL DIMENSION III | J10: =SUM(J4:J9) -> 1 | L10: =SUM(L7:L9) -> 0
B11: El proyecto siempre satisface y en la mayoría de sus propuestas supera las exigencias del programa. | C11: Excelente | D11: 5
H12: OBSERVACIONES GENERALES:
A13: Las observaciones derivadas de esta Pauta en sus cuadros de fortalezas y debilidades, así como en Observaciones Generales serán consideradas como parte del seguimiento de la supervisión técnica que se realizará una vez adjudicado el proyecto y puesto en marcha.
A15: I. DATOS GENERALES
A16: PERIODO DE EVALUACIÓN
A17: NOMBRE DEL PROYECTO
A18: EJE ESTRATÉGICO AL CUAL SE DIRIGE
A19: PUNTAJE FINAL | B19: =L10 -> 0
A23: 1.- | B23: Criterio : Relación del proyecto con los ejes estratégicos de la organización | C23: Ponderador % (A) | D23: Puntaje (B) | E23: (% puntaje) (C)
B24: DESCRIPTORES
A25: 1 | B25: Analiza de manera objetiva los ejes estratégicos correspondientes a la Municipalidad. | C25: 0.2 | E25: =(D25*C25) -> 0
A26: 2 | B26: Relaciona el proyecto con un eje estratégico de la organización. | C26: 0.3 | E26: =(D26*C26) -> 0
A27: 3 | B27: Define el propósito del proyecto con la finalidad de establecer que problema específico resolverá. | C27: 0.2 | E27: =(D27*C27) -> 0
A28: 4 | B28: Declara con claridad el proyecto con el fin de entender el propósito del mismo. | C28: 0.3 | E28: =(D28*C28) -> 0
B29: PUNTAJE TOTAL | C29: =SUM(C25:C28) -> 1 | E29: =SUM(E25:E28) -> 0
B31: Observaciones: fundamente brevemente la calificación asignada
B32: Fortalezas | C32: Debilidades
A37: 2.- | B37: Criterio : Analiza el mercado objetivo del proyecto | C37: Ponderador % (A) | D37: Puntaje (B) | E37: (% puntaje) (C)
B38: DESCRIPTORES
A39: 1 | B39: Realiza un instrumento para la realización del Estudio de Mercado para conocer la aceptación del proyecto en la comunidad | C39: 0.25 | E39: =(D39*C39) -> 0
A40: 2 | B40: Identifica aspectos relevantes para la realización del proyecto en base al Estudio de Mercado. | C40: 0.25 | E40: =(D40*C40) -> 0
A41: 3 | B41: Identifica el tamaño de la muestra según los parámetros expuestos por el docente. | C41: 0.2 | E41: =(D41*C41) -> 0
A42: 4 | B42: Analiza de manera genérica la competencia, con el fin de obtener referencias en el precio del producto. | C42: 0.1 | E42: =(D42*C42) -> 0
A43: 5 | B43: Determina la comercialización del producto en base a criterios acordes al tipo de producto a ofrecer | C43: 0.2 | E43: =(D43*C43) -> 0
B44: PUNTAJE TOTAL | C44: =SUM(C39:C43) -> 1 | E44: =SUM(E39:E43) -> 0
B46: Observaciones: fundamente brevemente la calificación asignada
B47: Fortalezas | C47: Debilidades
A52: 3.- | B52: Criterio : Establece los recursos óptimos para el desarrollo del proyecto | C52: Ponderador % (A) | D52: Puntaje (B) | E52: (% puntaje) (C)
B53: DESCRIPTORES
A54: 1 | B54: Identifica los recursos humanos necesarios para el desarrollo del proyecto | C54: 0.2 | E54: =(D54*C54) -> 0
A55: 2 | B55: Identifica los recursos materiales necesarios para el desarrollo del proyecto | C55: 0.2 | E55: =(D55*C55) -> 0
A56: 3 | B56: Identifica la infraestructura necesaria para el desarrollo del proyecto | C56: 0.2 | E56: =(D56*C56) -> 0
A57: 4 | B57: Identifica los aspectos legales necesarios para el desarrollo del proyecto. | C57: 0.2 | E57: =(D57*C57) -> 0
A58: 5 | B58: Justifica la determinación geográfica del proyecto basados en una tabla comparativa con ponderación de los aspectos a evaluar. | C58: 0.2 | E58: =(D58*C58) -> 0
B59: PUNTAJE TOTAL | C59: =SUM(C54:C58) -> 1 | E59: =SUM(E54:E58) -> 0
B61: Observaciones: fundamente brevemente la calificación asignada
B62: Fortalezas | C62: Debilidades
A68: 4.- | B68: Criterio: Relaciona los recursos con las actividades a desarrollar en el proyecto | C68: Ponderador % (A) | D68: Puntaje (B) | E68: (% puntaje) (C)
B69: DESCRIPTORES
A70: 1 | B70: Desarrolla la EDT del proyecto analizando las actividades involucradas en el mismo | C70: 0.15 | E70: =(D70*C70) -> 0
A71: 2 | B71: Genera un cronograma de actividades estableciendo etapas de acuerdo a las necesidades del proyecto | C71: 0.2 | E71: =(D71*C71) -> 0
A72: 3 | B72: Establece actividades relacionadas a la magnitud del proyecto | C72: 0.3 | E72: =(D72*C72) -> 0
A73: 4 | B73: Realiza un resumen de costos en recursos humanos, en relación a las actividades expresadas en el cronograma | C73: 0.1 | E73: =(D73*C73) -> 0
A74: 5 | B74: Realiza el cálculo de Reserva de contingencia acorde a los riesgos identificados por el equipo | C74: 0.15 | E74: =(D74*C74) -> 0
A75: 6 | B75: Determina factores ambientales para el cálculo de los costos asociados al proyecto. | C75: 0.1 | E75: =(D75*C75) -> 0
B76: PUNTAJE TOTAL | C76: =SUM(C70:C75) -> 1 | E76: =SUM(E70:E75) -> 0
B78: Observaciones: fundamente brevemente la calificación asignada
B79: Fortalezas | C79: Debilidades
A84: 5.- | B84: Criterio : Establece conceptos económicos relacionados con el proyecto | C84: Ponderador % (A) | D84: Puntaje (B) | E84: (% puntaje) (C)
A85: 1 | B85: La estructura del flujo de caja es acorde al proyecto a realizar | C85: 0.05 | E85: =(D85*C85) -> 0
A86: 2 | B86: Establece valores en el flujo de caja acordes a las necesidades del proyecto | C86: 0.15 | E86: =(D86*C86) -> 0
A87: 3 | B87: Realiza las operaciones matemáticas de manera correcta dentro del flujo de caja | C87: 0.1 | E87: =(D87*C87) -> 0
A88: 4 | B88: Establece una inversión inicial acorde a las necesidades del proyecto | C88: 0.1 | E88: =(D88*C88) -> 0
A89: 5 | B89: Establece el punto de equilibrio de manera correcta de acuerdo a los datos del proyecto | C89: 0.1 | E89: =(D89*C89) -> 0
A90: 6 | B90: Establece el período de recuperación de capital de manera correcta de acuerdo a los datos del proyecto | C90: 0.1 | E90: =(D90*C90) -> 0
A91: 7 | B91: Determina el VAN del proyecto de manera correcta de acuerdo a la información entregada en el flujo de caja | C91: 0.15 | E91: =(D91*C91) -> 0
A92: 8 | B92: Determina la TIR de manera correcta de acuerdo a la información entregada en el flujo de caja | C92: 0.15 | E92: =(D92*C92) -> 0
A93: 9 | B93: Establece de manera correcta las cuotas del préstamo a pagar para cubrir la inversión inicial en relación al porcentaje solicitado | C93: 0.1 | E93: =(D93*C93) -> 0
B94: PUNTAJE TOTAL | C94: =SUM(C85:C93) -> 1 | E94: =SUM(E85:E93) -> 0
B96: Observaciones: fundamente brevemente la calificación asignada
B97: Fortalezas | C97: Debilidades
A102: 6.- | B102: Criterio : Determina factores económicos que demuestran la factibilidad del proyecto | C102: Ponderador % (A) | D102: Puntaje (B) | E102: (% puntaje) (C)
B103: DESCRIPTORES
A104: a | B104: El período de recuperación es acorde a la duración del proyecto | C104: 0.2 | E104: =(D104*C104) -> 0
A105: b | B105: La TIR es positiva, determinando que el proyecto es conveniente realizarlo | C105: 0.4 | E105: =(D105*C105) -> 0
A106: c | B106: La VAN es positiva, determinando que el proyecto es conveniente realizarlo | C106: 0.4 | E106: =(D106*C106) -> 0
B107: PUNTAJE TOTAL | C107: =SUM(C104:C106) -> 1 | E107: =SUM(E104:E106) -> 0
B109: Observaciones: fundamente brevemente la calificación asignada
B110: Fortalezas | C110: Debilidades

Sheet PAUTA 5
A1: Pauta de Evaluación de Proyectos | H1: RESUMEN DE LOGRO EVALUACION POR DIMENSIÓN
A3: La escala para la asignación de puntajes en cada descriptor de los criterios a evaluar irá de 1 a 5 con las siguientes consideraciones: | H3: Número | I3: DIMENSION A EVALUAR | J3: Ponderación | K3: Puntaje | L3: (%puntaje)*20
H4: 1 | I4: Ejes estratégicos | J4: 0.2 | K4: =E29 -> 0 | L4: =(K4*J4) -> 0
B5: ESCALA DE PUNTAJES DE EVALUACION | H5: 2 | I5: Análisis de Mercado | J5: 0.1 | K5: =E44 -> 0 | L5: =(K5*J5) -> 0
B6: DEFINICIÓN | C6: CATEGORÍA | D6: PUNTAJE | H6: 3 | I6: Análisis de Recursos | J6: 0.1 | K6: =E59 -> 0 | L6: =(K6*J6) -> 0
B7: El proyecto no cumple las exigencias del programa. | C7: Deficiente | D7: 1 | H7: 4 | I7: Actividades del proyecto | J7: 0.1 | K7: =E76 -> 0 | L7: =(K7*J7) -> 0
B8: El proyecto presenta debilidades significativas respecto de las exigencias del programa. | C8: Insuficiente | D8: 2 | H8: 5 | I8: Conceptos Económicos | J8: 0.2 | K8: =E94 -> 0 | L8: =(K8*J8) -> 0
B9: El proyecto se ajusta mínimamente a las exigencias del programa y no satisface lo requerido. | C9: Regular | D9: 3 | H9: 6 | I9: Rentabilidad Económica | J9: 0.3 | K9: =E107 -> 0 | L9: =(K9*J9) -> 0
B10: El proyecto satisface y a veces supera las exigencias del programa. | C10: Bueno | D10: 4 | I10: TOTAL DIMENSION III | J10: =SUM(J4:J9) -> 1 | L10: =SUM(L7:L9) -> 0
B11: El proyecto siempre satisface y en la mayoría de sus propuestas supera las exigencias del programa. | C11: Excelente | D11: 5
H12: OBSERVACIONES GENERALES:
A13: Las observaciones derivadas de esta Pauta en sus cuadros de fortalezas y debilidades, así como en Observaciones Generales serán consideradas como parte del seguimiento de la supervisión técnica que se realizará una vez adjudicado el proyecto y puesto en marcha.
A15: I. DATOS GENERALES
A16: PERIODO DE EVALUACIÓN
A17: NOMBRE DEL PROYECTO
A18: EJE ESTRATÉGICO AL CUAL SE DIRIGE
A19: PUNTAJE FINAL | B19: =L10 -> 0
A23: 1.- | B23: Criterio : Relación del proyecto con los ejes estratégicos de la organización | C23: Ponderador % (A) | D23: Puntaje (B) | E23: (% puntaje) (C)
B24: DESCRIPTORES
A25: 1 | B25: Analiza de manera objetiva los ejes estratégicos correspondientes a la Municipalidad. | C25: 0.2 | E25: =(D25*C25) -> 0
A26: 2 | B26: Relaciona el proyecto con un eje estratégico de la organización. | C26: 0.3 | E26: =(D26*C26) -> 0
A27: 3 | B27: Define el propósito del proyecto con la finalidad de establecer que problema específico resolverá. | C27: 0.2 | E27: =(D27*C27) -> 0
A28: 4 | B28: Declara con claridad el proyecto con el fin de entender el propósito del mismo. | C28: 0.3 | E28: =(D28*C28) -> 0
B29: PUNTAJE TOTAL | C29: =SUM(C25:C28) -> 1 | E29: =SUM(E25:E28) -> 0
B31: Observaciones: fundamente brevemente la calificación asignada
B32: Fortalezas | C32: Debilidades
A37: 2.- | B37: Criterio : Analiza el mercado objetivo del proyecto | C37: Ponderador % (A) | D37: Puntaje (B) | E37: (% puntaje) (C)
B38: DESCRIPTORES
A39: 1 | B39: Realiza un instrumento para la realización del Estudio de Mercado para conocer la aceptación del proyecto en la comunidad | C39: 0.25 | E39: =(D39*C39) -> 0
A40: 2 | B40: Identifica aspectos relevantes para la realización del proyecto en base al Estudio de Mercado. | C40: 0.25 | E40: =(D40*C40) -> 0
A41: 3 | B41: Identifica el tamaño de la muestra según los parámetros expuestos por el docente. | C41: 0.2 | E41: =(D41*C41) -> 0
A42: 4 | B42: Analiza de manera genérica la competencia, con el fin de obtener referencias en el precio del producto. | C42: 0.1 | E42: =(D42*C42) -> 0
A43: 5 | B43: Determina la comercialización del producto en base a criterios acordes al tipo de producto a ofrecer | C43: 0.2 | E43: =(D43*C43) -> 0
B44: PUNTAJE TOTAL | C44: =SUM(C39:C43) -> 1 | E44: =SUM(E39:E43) -> 0
B46: Observaciones: fundamente brevemente la calificación asignada
B47: Fortalezas | C47: Debilidades
A52: 3.- | B52: Criterio : Establece los recursos óptimos para el desarrollo del proyecto | C52: Ponderador % (A) | D52: Puntaje (B) | E52: (% puntaje) (C)
B53: DESCRIPTORES
A54: 1 | B54: Identifica los recursos humanos necesarios para el desarrollo del proyecto | C54: 0.2 | E54: =(D54*C54) -> 0
A55: 2 | B55: Identifica los recursos materiales necesarios para el desarrollo del proyecto | C55: 0.2 | E55: =(D55*C55) -> 0
A56: 3 | B56: Identifica la infraestructura necesaria para el desarrollo del proyecto | C56: 0.2 | E56: =(D56*C56) -> 0
A57: 4 | B57: Identifica los aspectos legales necesarios para el desarrollo del proyecto. | C57: 0.2 | E57: =(D57*C57) -> 0
A58: 5 | B58: Justifica la determinación geográfica del proyecto basados en una tabla comparativa con ponderación de los aspectos a evaluar. | C58: 0.2 | E58: =(D58*C58) -> 0
B59: PUNTAJE TOTAL | C59: =SUM(C54:C58) -> 1 | E59: =SUM(E54:E58) -> 0
B61: Observaciones: fundamente brevemente la calificación asignada
B62: Fortalezas | C62: Debilidades
A68: 4.- | B68: Criterio: Relaciona los recursos con las actividades a desarrollar en el proyecto | C68: Ponderador % (A) | D68: Puntaje (B) | E68: (% puntaje) (C)
B69: DESCRIPTORES
A70: 1 | B70: Desarrolla la EDT del proyecto analizando las actividades involucradas en el mismo | C70: 0.15 | E70: =(D70*C70) -> 0
A71: 2 | B71: Genera un cronograma de actividades estableciendo etapas de acuerdo a las necesidades del proyecto | C71: 0.2 | E71: =(D71*C71) -> 0
A72: 3 | B72: Establece actividades relacionadas a la magnitud del proyecto | C72: 0.3 | E72: =(D72*C72) -> 0
A73: 4 | B73: Realiza un resumen de costos en recursos humanos, en relación a las actividades expresadas en el cronograma | C73: 0.1 | E73: =(D73*C73) -> 0
A74: 5 | B74: Realiza el cálculo de Reserva de contingencia acorde a los riesgos identificados por el equipo | C74: 0.15 | E74: =(D74*C74) -> 0
A75: 6 | B75: Determina factores ambientales para el cálculo de los costos asociados al proyecto. | C75: 0.1 | E75: =(D75*C75) -> 0
B76: PUNTAJE TOTAL | C76: =SUM(C70:C75) -> 1 | E76: =SUM(E70:E75) -> 0
B78: Observaciones: fundamente brevemente la calificación asignada
B79: Fortalezas | C79: Debilidades
A84: 5.- | B84: Criterio : Establece conceptos económicos relacionados con el proyecto | C84: Ponderador % (A) | D84: Puntaje (B) | E84: (% puntaje) (C)
A85: 1 | B85: La estructura del flujo de caja es acorde al proyecto a realizar | C85: 0.05 | E85: =(D85*C85) -> 0
A86: 2 | B86: Establece valores en el flujo de caja acordes a las necesidades del proyecto | C86: 0.15 | E86: =(D86*C86) -> 0
A87: 3 | B87: Realiza las operaciones matemáticas de manera correcta dentro del flujo de caja | C87: 0.1 | E87: =(D87*C87) -> 0
A88: 4 | B88: Establece una inversión inicial acorde a las necesidades del proyecto | C88: 0.1 | E88: =(D88*C88) -> 0
A89: 5 | B89: Establece el punto de equilibrio de manera correcta de acuerdo a los datos del proyecto | C89: 0.1 | E89: =(D89*C89) -> 0
A90: 6 | B90: Establece el período de recuperación de capital de manera correcta de acuerdo a los datos del proyecto | C90: 0.1 | E90: =(D90*C90) -> 0
A91: 7 | B91: Determina el VAN del proyecto de manera correcta de acuerdo a la información entregada en el flujo de caja | C91: 0.15 | E91: =(D91*C91) -> 0
A92: 8 | B92: Determina la TIR de manera correcta de acuerdo a la información entregada en el flujo de caja | C92: 0.15 | E92: =(D92*C92) -> 0
A93: 9 | B93: Establece de manera correcta las cuotas del préstamo a pagar para cubrir la inversión inicial en relación al porcentaje solicitado | C93: 0.1 | E93: =(D93*C93) -> 0
B94: PUNTAJE TOTAL | C94: =SUM(C85:C93) -> 1 | E94: =SUM(E85:E93) -> 0
B96: Observaciones: fundamente brevemente la calificación asignada
B97: Fortalezas | C97: Debilidades
A102: 6.- | B102: Criterio : Determina factores económicos que demuestran la factibilidad del proyecto | C102: Ponderador % (A) | D102: Puntaje (B) | E102: (% puntaje) (C)
B103: DESCRIPTORES
A104: a | B104: El período de recuperación es acorde a la duración del proyecto | C104: 0.2 | E104: =(D104*C104) -> 0
A105: b | B105: La TIR es positiva, determinando que el proyecto es conveniente realizarlo | C105: 0.4 | E105: =(D105*C105) -> 0
A106: c | B106: La VAN es positiva, determinando que el proyecto es conveniente realizarlo | C106: 0.4 | E106: =(D106*C106) -> 0
B107: PUNTAJE TOTAL | C107: =SUM(C104:C106) -> 1 | E107: =SUM(E104:E106) -> 0
B109: Observaciones: fundamente brevemente la calificación asignada
B110: Fortalezas | C110: Debilidades

Sheet PAUTA 6
A1: Pauta de Evaluación de Proyectos | H1: RESUMEN DE LOGRO EVALUACION POR DIMENSIÓN
A3: La escala para la asignación de puntajes en cada descriptor de los criterios a evaluar irá de 1 a 5 con las siguientes consideraciones: | H3: Número | I3: DIMENSION A EVALUAR | J3: Ponderación | K3: Puntaje | L3: (%puntaje)*20
H4: 1 | I4: Ejes estratégicos | J4: 0.2 | K4: =E29 -> 0 | L4: =(K4*J4) -> 0
B5: ESCALA DE PUNTAJES DE EVALUACION | H5: 2 | I5: Análisis de Mercado | J5: 0.1 | K5: =E44 -> 0 | L5: =(K5*J5) -> 0
B6: DEFINICIÓN | C6: CATEGORÍA | D6: PUNTAJE | H6: 3 | I6: Análisis de Recursos | J6: 0.1 | K6: =E59 -> 0 | L6: =(K6*J6) -> 0
B7: El proyecto no cumple las exigencias del programa. | C7: Deficiente | D7: 1 | H7: 4 | I7: Actividades del proyecto | J7: 0.1 | K7: =E76 -> 0 | L7: =(K7*J7) -> 0
B8: El proyecto presenta debilidades significativas respecto de las exigencias del programa. | C8: Insuficiente | D8: 2 | H8: 5 | I8: Conceptos Económicos | J8: 0.2 | K8: =E94 -> 0 | L8: =(K8*J8) -> 0
B9: El proyecto se ajusta mínimamente a las exigencias del programa y no satisface lo requerido. | C9: Regular | D9: 3 | H9: 6 | I9: Rentabilidad Económica | J9: 0.3 | K9: =E107 -> 0 | L9: =(K9*J9) -> 0
B10: El proyecto satisface y a veces supera las exigencias del programa. | C10: Bueno | D10: 4 | I10: TOTAL DIMENSION III | J10: =SUM(J4:J9) -> 1 | L10: =SUM(L7:L9) -> 0
B11: El proyecto siempre satisface y en la mayoría de sus propuestas supera las exigencias del programa. | C11: Excelente | D11: 5
H12: OBSERVACIONES GENERALES:
A13: Las observaciones derivadas de esta Pauta en sus cuadros de fortalezas y debilidades, así como en Observaciones Generales serán consideradas como parte del seguimiento de la supervisión técnica que se realizará una vez adjudicado el proyecto y puesto en marcha.
A15: I. DATOS GENERALES
A16: PERIODO DE EVALUACIÓN
A17: NOMBRE DEL PROYECTO
A18: EJE ESTRATÉGICO AL CUAL SE DIRIGE
A19: PUNTAJE FINAL | B19: =L10 -> 0
A23: 1.- | B23: Criterio : Relación del proyecto con los ejes estratégicos de la organización | C23: Ponderador % (A) | D23: Puntaje (B) | E23: (% puntaje) (C)
B24: DESCRIPTORES
A25: 1 | B25: Analiza de manera objetiva los ejes estratégicos correspondientes a la Municipalidad. | C25: 0.2 | E25: =(D25*C25) -> 0
A26: 2 | B26: Relaciona el proyecto con un eje estratégico de la organización. | C26: 0.3 | E26: =(D26*C26) -> 0
A27: 3 | B27: Define el propósito del proyecto con la finalidad de establecer que problema específico resolverá. | C27: 0.2 | E27: =(D27*C27) -> 0
A28: 4 | B28: Declara con claridad el proyecto con el fin de entender el propósito del mismo. | C28: 0.3 | E28: =(D28*C28) -> 0
B29: PUNTAJE TOTAL | C29: =SUM(C25:C28) -> 1 | E29: =SUM(E25:E28) -> 0
B31: Observaciones: fundamente brevemente la calificación asignada
B32: Fortalezas | C32: Debilidades
A37: 2.- | B37: Criterio : Analiza el mercado objetivo del proyecto | C37: Ponderador % (A) | D37: Puntaje (B) | E37: (% puntaje) (C)
B38: DESCRIPTORES
A39: 1 | B39: Realiza un instrumento para la realización del Estudio de Mercado para conocer la aceptación del proyecto en la comunidad | C39: 0.25 | E39: =(D39*C39) -> 0
A40: 2 | B40: Identifica aspectos relevantes para la realización del proyecto en base al Estudio de Mercado. | C40: 0.25 | E40: =(D40*C40) -> 0
A41: 3 | B41: Identifica el tamaño de la muestra según los parámetros expuestos por el docente. | C41: 0.2 | E41: =(D41*C41) -> 0
A42: 4 | B42: Analiza de manera genérica la competencia, con el fin de obtener referencias en el precio del producto. | C42: 0.1 | E42: =(D42*C42) -> 0
A43: 5 | B43: Determina la comercialización del producto en base a criterios acordes al tipo de producto a ofrecer | C43: 0.2 | E43: =(D43*C43) -> 0
B44: PUNTAJE TOTAL | C44: =SUM(C39:C43) -> 1 | E44: =SUM(E39:E43) -> 0
B46: Observaciones: fundamente brevemente la calificación asignada
B47: Fortalezas | C47: Debilidades
A52: 3.- | B52: Criterio : Establece los recursos óptimos para el desarrollo del proyecto | C52: Ponderador % (A) | D52: Puntaje (B) | E52: (% puntaje) (C)
B53: DESCRIPTORES
A54: 1 | B54: Identifica los recursos humanos necesarios para el desarrollo del proyecto | C54: 0.2 | E54: =(D54*C54) -> 0
A55: 2 | B55: Identifica los recursos materiales necesarios para el desarrollo del proyecto | C55: 0.2 | E55: =(D55*C55) -> 0
A56: 3 | B56: Identifica la infraestructura necesaria para el desarrollo del proyecto | C56: 0.2 | E56: =(D56*C56) -> 0
A57: 4 | B57: Identifica los aspectos legales necesarios para el desarrollo del proyecto. | C57: 0.2 | E57: =(D57*C57) -> 0
A58: 5 | B58: Justifica la determinación geográfica del proyecto basados en una tabla comparativa con ponderación de los aspectos a evaluar. | C58: 0.2 | E58: =(D58*C58) -> 0
B59: PUNTAJE TOTAL | C59: =SUM(C54:C58) -> 1 | E59: =SUM(E54:E58) -> 0
B61: Observaciones: fundamente brevemente la calificación asignada
B62: Fortalezas | C62: Debilidades
A68: 4.- | B68: Criterio: Relaciona los recursos con las actividades a desarrollar en el proyecto | C68: Ponderador % (A) | D68: Puntaje (B) | E68: (% puntaje) (C)
B69: DESCRIPTORES
A70: 1 | B70: Desarrolla la EDT del proyecto analizando las actividades involucradas en el mismo | C70: 0.15 | E70: =(D70*C70) -> 0
A71: 2 | B71: Genera un cronograma de actividades estableciendo etapas de acuerdo a las necesidades del proyecto | C71: 0.2 | E71: =(D71*C71) -> 0
A72: 3 | B72: Establece actividades relacionadas a la magnitud del proyecto | C72: 0.3 | E72: =(D72*C72) -> 0
A73: 4 | B73: Realiza un resumen de costos en recursos humanos, en relación a las actividades expresadas en el cronograma | C73: 0.1 | E73: =(D73*C73) -> 0
A74: 5 | B74: Realiza el cálculo de Reserva de contingencia acorde a los riesgos identificados por el equipo | C74: 0.15 | E74: =(D74*C74) -> 0
A75: 6 | B75: Determina factores ambientales para el cálculo de los costos asociados al proyecto. | C75: 0.1 | E75: =(D75*C75) -> 0
B76: PUNTAJE TOTAL | C76: =SUM(C70:C75) -> 1 | E76: =SUM(E70:E75) -> 0
B78: Observaciones: fundamente brevemente la calificación asignada
B79: Fortalezas | C79: Debilidades
A84: 5.- | B84: Criterio : Establece conceptos económicos relacionados con el proyecto | C84: Ponderador % (A) | D84: Puntaje (B) | E84: (% puntaje) (C)
A85: 1 | B85: La estructura del flujo de caja es acorde al proyecto a realizar | C85: 0.05 | E85: =(D85*C85) -> 0
A86: 2 | B86: Establece valores en el flujo de caja acordes a las necesidades del proyecto | C86: 0.15 | E86: =(D86*C86) -> 0
A87: 3 | B87: Realiza las operaciones matemáticas de manera correcta dentro del flujo de caja | C87: 0.1 | E87: =(D87*C87) -> 0
A88: 4 | B88: Establece una inversión inicial acorde a las necesidades del proyecto | C88: 0.1 | E88: =(D88*C88) -> 0
A89: 5 | B89: Establece el punto de equilibrio de manera correcta de acuerdo a los datos del proyecto | C89: 0.1 | E89: =(D89*C89) -> 0
A90: 6 | B90: Establece el período de recuperación de capital de manera correcta de acuerdo a los datos del proyecto | C90: 0.1 | E90: =(D90*C90) -> 0
A91: 7 | B91: Determina el VAN del proyecto de manera correcta de acuerdo a la información entregada en el flujo de caja | C91: 0.15 | E91: =(D91*C91) -> 0
A92: 8 | B92: Determina la TIR de manera correcta de acuerdo a la información entregada en el flujo de caja | C92: 0.15 | E92: =(D92*C92) -> 0
A93: 9 | B93: Establece de manera correcta las cuotas del préstamo a pagar para cubrir la inversión inicial en relación al porcentaje solicitado | C93: 0.1 | E93: =(D93*C93) -> 0
B94: PUNTAJE TOTAL | C94: =SUM(C85:C93) -> 1 | E94: =SUM(E85:E93) -> 0
B96: Observaciones: fundamente brevemente la calificación asignada
B97: Fortalezas | C97: Debilidades
A102: 6.- | B102: Criterio : Determina factores económicos que demuestran la factibilidad del proyecto | C102: Ponderador % (A) | D102: Puntaje (B) | E102: (% puntaje) (C)
B103: DESCRIPTORES
A104: a | B104: El período de recuperación es acorde a la duración del proyecto | C104: 0.2 | E104: =(D104*C104) -> 0
A105: b | B105: La TIR es positiva, determinando que el proyecto es conveniente realizarlo | C105: 0.4 | E105: =(D105*C105) -> 0
A106: c | B106: La VAN es positiva, determinando que el proyecto es conveniente realizarlo | C106: 0.4 | E106: =(D106*C106) -> 0
B107: PUNTAJE TOTAL | C107: =SUM(C104:C106) -> 1 | E107: =SUM(E104:E106) -> 0
B109: Observaciones: fundamente brevemente la calificación asignada
B110: Fortalezas | C110: Debilidades

Sheet PUNTAJES FINALES
C3: Número | D3: NOMBRE DEL PROYECTO | E3: PUNTAJ FINAL
C4: 1 | D4: =+'PAUTA 1'!B17 -> Pagina Web Hostal-Soft | E4: ='PAUTA 1'!B19 -> 5
C5: 2 | D5: =+'PAUTA 2'!B17 | E5: ='PAUTA 2'!B19 -> 0
C6: 3 | D6: =+'PAUTA 3'!B17 -> Web Movil Hostal-Soft | E6: ='PAUTA 3'!B19 -> 4.58
C7: 4 | D7: =+'PAUTA 4'!B17 | E7: ='PAUTA 4'!B19:E19
C8: 5 | D8: =+'PAUTA 5'!B17 | E8: ='PAUTA 5'!B19:E19
C9: 6 | D9: =+'PAUTA 6'!B17 | E9: ='PAUTA 6'!B19:E19
C11: OBSERVACIONES GENERALES:
